MANIFEST.in
pypi.rst
setup.py
django_exclusivebooleanfield.egg-info/PKG-INFO
django_exclusivebooleanfield.egg-info/SOURCES.txt
django_exclusivebooleanfield.egg-info/dependency_links.txt
django_exclusivebooleanfield.egg-info/requires.txt
django_exclusivebooleanfield.egg-info/top_level.txt
exclusivebooleanfield/__init__.py
exclusivebooleanfield/fields.py